linguacraft/__init__.py
linguacraft/known_words.py
linguacraft/main.py
linguacraft/styles.tcss
linguacraft/text_processing.py
linguacraft/translation.py
linguacraft/translation_bulk.py
LinguaCraft-0.1.3.dist-info/LICENSE.txt
LinguaCraft-0.1.3.dist-info/METADATA
LinguaCraft-0.1.3.dist-info/WHEEL
LinguaCraft-0.1.3.dist-info/entry_points.txt
LinguaCraft-0.1.3.dist-info/top_level.txt
LinguaCraft-0.1.3.dist-info/RECORD
