Metadata-Version: 2.1
Name: LinguaCraft
Version: 0.1.3
Summary: A personalized companion for mastering foreign languages.
Home-page: https://github.com/dimanngo/LinguaCraft
Author: Dmytro Golodiuk
Author-email: info@golodiuk.com
Classifier: Programming Language :: Python :: 3
Classifier: License :: OSI Approved :: MIT License
Classifier: Operating System :: OS Independent
Requires-Python: >=3.6
License-File: LICENSE.txt
Requires-Dist: deep-translator
Requires-Dist: langdetect
Requires-Dist: nltk
Requires-Dist: openai
Requires-Dist: python-dotenv
Requires-Dist: requests
Requires-Dist: rich
Requires-Dist: spacy
Requires-Dist: textual
